trrc/__init__.py
trrc/__main__.py
trrc/config_opts.py
trrc/create_parser.py
trrc/parser_opts.py
trrc/some.py
trrc/utils.py
trrc-0.1.3.data/data/share/bash-completion/completions/trrc
trrc-0.1.3.data/data/share/man/man1/trrc.1
trrc-0.1.3.data/data/share/zsh/site-functions/_trrc
trrc-0.1.3.dist-info/LICENSE
trrc-0.1.3.dist-info/METADATA
trrc-0.1.3.dist-info/WHEEL
trrc-0.1.3.dist-info/entry_points.txt
trrc-0.1.3.dist-info/top_level.txt
trrc-0.1.3.dist-info/RECORD
