Metadata-Version: 2.1
Name: trrc
Version: 0.1.3
Summary: a command-line program for creating anki card using AnkiConnect API.
Home-page: https://github.com/Constantin1489/trrc
Author: Constantin Hong
Author-email: Constantin Hong <hongconstantin@gmail.com>
Maintainer: Constantin Hong
Maintainer-email: Constantin Hong <hongconstantin@gmail.com>
License: GNU GENERAL PUBLIC LICENSE
Project-URL: Homepage, https://github.com/Constantin1489/trrc
Project-URL: Bug Tracker, https://github.com/Constantin1489/trrc/issues
Project-URL: Documentation, https://github.com/Constantin1489/trrc#readme
Classifier: Intended Audience :: Education
Classifier: Development Status :: 3 - Alpha
Classifier: Environment :: Console
Classifier: Topic :: Education
Classifier: Topic :: Internet :: WWW/HTTP
Classifier: Topic :: Utilities
Classifier: Operating System :: MacOS :: MacOS X
Classifier: Operating System :: POSIX :: Linux
Classifier: License :: OSI Approved :: GNU General Public License v3 (GPLv3)
Classifier: Programming Language :: Python
Classifier: Programming Language :: Python :: 3.9
Classifier: Programming Language :: Python :: 3.10
Classifier: Programming Language :: Python :: 3.11
Requires-Python: >=3.9
License-File: LICENSE
Requires-Dist: requests
Requires-Dist: tomlkit
Requires-Dist: tomli-w
